{
  "data": [
    {
      "section": "czlonkowie-rodziny-po-angielsku",
      "language": "English",
      "translationLanguage": "Polish",
      "word": "brother",
      "translation": "",
      "definition": "",
      "definition_translation": "",
      "example": "",
      "example_translation": "",
      "imageLink": "https://www.ang.pl/img/slownik/brother.jpg",
      "audioLink": "https://www.ang.pl/sound/dict/brother.mp3"
    },
    {
      "section": "czlonkowie-rodziny-po-angielsku",
      "language": "English",
      "translationLanguage": "Polish",
      "word": "child",
      "translation": "dziecko",
      "definition": "a human being between birth and puberty",
      "definition_translation": "człowiek między urodzeniem a dojrzałością",
      "example": "She's a very clever child.",
      "example_translation": "Ona jest bardzo inteligentnym dzieckiem.",
      "imageLink": "https://www.ang.pl/img/slownik/child.jpg",
      "audioLink": "https://www.ang.pl/sound/dict/child.mp3"
    },
    {
      "section": "czlonkowie-rodziny-po-angielsku",
      "language": "English",
      "translationLanguage": "Polish",
      "word": "children",
      "translation": "dzieci",
      "definition": "Plural form of child; young humans below the age of puberty",
      "definition_translation": "Forma liczby mnogiej dziecka; młodzi ludzie poniżej wieku dojrzałości",
      "example": "The children are playing in the park.",
      "example_translation": "Dzieci bawią się w parku.",
      "imageLink": "https://www.ang.pl/img/slownik/children.jpg",
      "audioLink": "https://www.ang.pl/sound/dict/children.mp3"
    },
    {
      "section": "czlonkowie-rodziny-po-angielsku",
      "language": "English",
      "translationLanguage": "Polish",
      "word": "dad",
      "translation": "tata",
      "definition": "a father or a male parent",
      "definition_translation": "ojciec lub rodzic męski",
      "example": "My dad is a teacher.",
      "example_translation": "Mój tata jest nauczycielem.",
      "imageLink": "https://www.ang.pl/img/slownik/dad.jpg",
      "audioLink": "https://www.ang.pl/sound/dict/dad.mp3"
    },
    {
      "section": "czlonkowie-rodziny-po-angielsku",
      "language": "English",
      "translationLanguage": "Polish",
      "word": "daughter",
      "translation": "córka",
      "definition": "A female child or a female descendant",
      "definition_translation": "Córka lub potomkini żeńska",
      "example": "My daughter is studying at university.",
      "example_translation": "Moja córka studiuje na uniwersytecie.",
      "imageLink": "https://www.ang.pl/img/slownik/daughter.jpg",
      "audioLink": "https://www.ang.pl/sound/dict/daughter.mp3"
    },
    {
      "section": "czlonkowie-rodziny-po-angielsku",
      "language": "English",
      "translationLanguage": "Polish",
      "word": "father",
      "translation": "ojciec",
      "definition": "a male parent or a person who gives care or guidance to someone",
      "definition_translation": "mężczyzna będący rodzicem lub osoba, która zapewnia opiekę lub poradę komuś",
      "example": "My father is a doctor.",
      "example_translation": "Mój ojciec jest lekarzem.",
      "imageLink": "https://www.ang.pl/img/slownik/father.jpg",
      "audioLink": "https://www.ang.pl/sound/dict/father.mp3"
    },
    {
      "section": "czlonkowie-rodziny-po-angielsku",
      "language": "English",
      "translationLanguage": "Polish",
      "word": "husband",
      "translation": "mąż",
      "definition": "a male partner in a marriage",
      "definition_translation": "męski partner w małżeństwie",
      "example": "My husband is a great cook.",
      "example_translation": "Mój mąż jest wielkim kucharzem.",
      "imageLink": "https://www.ang.pl/img/slownik/husband.jpg",
      "audioLink": "https://www.ang.pl/sound/dict/husband.mp3"
    },
    {
      "section": "czlonkowie-rodziny-po-angielsku",
      "language": "English",
      "translationLanguage": "Polish",
      "word": "mother",
      "translation": "matka",
      "definition": "A woman in relation to a child or children to whom she has given birth.",
      "definition_translation": "Kobieta w stosunku do dziecka lub dzieci, którym urodziła.",
      "example": "My mother is a great cook.",
      "example_translation": "Moja matka jest świetną kucharką.",
      "imageLink": "https://www.ang.pl/img/slownik/mother.jpg",
      "audioLink": "https://www.ang.pl/sound/dict/mother.mp3"
    },
    {
      "section": "czlonkowie-rodziny-po-angielsku",
      "language": "English",
      "translationLanguage": "Polish",
      "word": "mum",
      "translation": "mama",
      "definition": "a female parent",
      "definition_translation": "matka",
      "example": "My mum is very kind.",
      "example_translation": "Moja mama jest bardzo miła.",
      "imageLink": "https://www.ang.pl/img/slownik/mum.jpg",
      "audioLink": "https://www.ang.pl/sound/dict/mum.mp3"
    },
    {
      "section": "czlonkowie-rodziny-po-angielsku",
      "language": "English",
      "translationLanguage": "Polish",
      "word": "parents",
      "translation": "rodzice",
      "definition": "a father or mother",
      "definition_translation": "ojciec lub matka",
      "example": "My parents are coming to visit.",
      "example_translation": "Moja rodzice przyjadą na wizytę.",
      "imageLink": "https://www.ang.pl/img/slownik/parents.jpg",
      "audioLink": "https://www.ang.pl/sound/dict/parents.mp3"
    },
    {
      "section": "czlonkowie-rodziny-po-angielsku",
      "language": "English",
      "translationLanguage": "Polish",
      "word": "sister",
      "translation": "siostra",
      "definition": "a female sibling",
      "definition_translation": "żeński brat",
      "example": "My sister is studying at university.",
      "example_translation": "Moja siostra studiuje na uniwersytecie.",
      "imageLink": "https://www.ang.pl/img/slownik/sister.jpg",
      "audioLink": "https://www.ang.pl/sound/dict/sister.mp3"
    },
    {
      "section": "czlonkowie-rodziny-po-angielsku",
      "language": "English",
      "translationLanguage": "Polish",
      "word": "son",
      "translation": "syn",
      "definition": "a male child or a male descendant",
      "definition_translation": "męski potomek lub męski wnuk",
      "example": "My son is very smart.",
      "example_translation": "Mój syn jest bardzo inteligentny.",
      "imageLink": "https://www.ang.pl/img/slownik/son.jpg",
      "audioLink": "https://www.ang.pl/sound/dict/son.mp3"
    },
    {
      "section": "czlonkowie-rodziny-po-angielsku",
      "language": "English",
      "translationLanguage": "Polish",
      "word": "wife",
      "translation": "żona",
      "definition": "a married woman",
      "definition_translation": "kobieta zamężna",
      "example": "My wife is a doctor.",
      "example_translation": "Moja żona jest lekarzem.",
      "imageLink": "https://www.ang.pl/img/slownik/wife.jpg",
      "audioLink": "https://www.ang.pl/sound/dict/wife.mp3"
    },
    {
      "section": "czlonkowie-rodziny-po-angielsku",
      "language": "English",
      "translationLanguage": "Polish",
      "word": "aunt",
      "translation": "ciotka",
      "definition": "The sister of one's mother or father",
      "definition_translation": "Siostra matki lub ojca",
      "example": "My aunt lives in Paris.",
      "example_translation": "Moja ciotka mieszka w Paryżu.",
      "imageLink": "https://www.ang.pl/img/slownik/aunt.jpg",
      "audioLink": "https://www.ang.pl/sound/dict/aunt.mp3"
    },
    {
      "section": "czlonkowie-rodziny-po-angielsku",
      "language": "English",
      "translationLanguage": "Polish",
      "word": "big brother",
      "translation": "wielki brat",
      "definition": "an older brother, especially one who is protective or influential",
      "definition_translation": "starszy brat, szczególnie taki, który jest opiekuńczy lub wpływowy",
      "example": "My big brother always looks out for me.",
      "example_translation": "Mój wielki brat zawsze mi pomaga.",
      "imageLink": "https://www.ang.pl/img/slownik/big-brothersister.jpg",
      "audioLink": "https://www.ang.pl/sound/dict/big brother.mp3"
    },
    {
      "section": "czlonkowie-rodziny-po-angielsku",
      "language": "English",
      "translationLanguage": "Polish",
      "word": "big sister",
      "translation": "starsza siostra",
      "definition": "an older girl or woman who takes care of a younger person",
      "definition_translation": "starsza dziewczyna lub kobieta, która opiekuje się młodszą osobą",
      "example": "My big sister always helps me with my homework.",
      "example_translation": "Moja starsza siostra zawsze pomaga mi z zadaniem domowym.",
      "imageLink": "https://www.ang.pl/img/slownik/big-sister.jpg",
      "audioLink": "https://www.ang.pl/sound/dict/big sister.mp3"
    },
    {
      "section": "czlonkowie-rodziny-po-angielsku",
      "language": "English",
      "translationLanguage": "Polish",
      "word": "cousin",
      "translation": "",
      "definition": "",
      "definition_translation": "",
      "example": "",
      "example_translation": "",
      "imageLink": "https://www.ang.pl/img/slownik/cousin.jpg",
      "audioLink": "https://www.ang.pl/sound/dict/cousin.mp3"
    },
    {
      "section": "czlonkowie-rodziny-po-angielsku",
      "language": "English",
      "translationLanguage": "Polish",
      "word": "grandchild",
      "translation": "wnuczek",
      "definition": "a child of one's child",
      "definition_translation": "dziecko dziecka",
      "example": "My grandchild is very playful.",
      "example_translation": "Mój wnuczek jest bardzo zabawny.",
      "imageLink": "https://www.ang.pl/img/slownik/grandchild.jpg",
      "audioLink": "https://www.ang.pl/sound/dict/grandchild.mp3"
    },
    {
      "section": "czlonkowie-rodziny-po-angielsku",
      "language": "English",
      "translationLanguage": "Polish",
      "word": "grandchildren",
      "translation": "wnuki",
      "definition": "the children of one's child or children",
      "definition_translation": "dzieci własnego dziecka lub dzieci",
      "example": "She loves spending time with her grandchildren.",
      "example_translation": "Ona uwielbia spędzać czas ze swoimi wnukami.",
      "imageLink": "https://www.ang.pl/img/slownik/grandchildren.jpg",
      "audioLink": "https://www.ang.pl/sound/dict/grandchildren.mp3"
    },
    {
      "section": "czlonkowie-rodziny-po-angielsku",
      "language": "English",
      "translationLanguage": "Polish",
      "word": "granddad",
      "translation": "dziadek",
      "definition": "the father of one's mother or father",
      "definition_translation": "ojciec matki lub ojca",
      "example": "My granddad taught me how to fish.",
      "example_translation": "Mój dziadek nauczył mnie, jak łowić rybę.",
      "imageLink": "https://www.ang.pl/img/slownik/granddad.jpg",
      "audioLink": "https://www.ang.pl/sound/dict/granddad.mp3"
    },
    {
      "section": "czlonkowie-rodziny-po-angielsku",
      "language": "English",
      "translationLanguage": "Polish",
      "word": "granddaughter",
      "translation": "wnuczka",
      "definition": "a female child of one's child",
      "definition_translation": "córka dziecka",
      "example": "My granddaughter is very sweet.",
      "example_translation": "Moja wnuczka jest bardzo słodka.",
      "imageLink": "https://www.ang.pl/img/slownik/granddaughter.jpg",
      "audioLink": "https://www.ang.pl/sound/dict/granddaughter.mp3"
    },
    {
      "section": "czlonkowie-rodziny-po-angielsku",
      "language": "English",
      "translationLanguage": "Polish",
      "word": "grandfather",
      "translation": "dziadek",
      "definition": "the father of one's father or mother",
      "definition_translation": "ojciec ojca lub matki",
      "example": "My grandfather was a kind and wise man.",
      "example_translation": "Mój dziadek był łagodnym i mądrym człowiekiem.",
      "imageLink": "https://www.ang.pl/img/slownik/grandfather.jpg",
      "audioLink": "https://www.ang.pl/sound/dict/grandfather.mp3"
    },
    {
      "section": "czlonkowie-rodziny-po-angielsku",
      "language": "English",
      "translationLanguage": "Polish",
      "word": "grandma",
      "translation": "",
      "definition": "",
      "definition_translation": "",
      "example": "",
      "example_translation": "",
      "imageLink": "https://www.ang.pl/img/slownik/grandma.jpg",
      "audioLink": "https://www.ang.pl/sound/dict/grandma.mp3"
    },
    {
      "section": "czlonkowie-rodziny-po-angielsku",
      "language": "English",
      "translationLanguage": "Polish",
      "word": "grandmother",
      "translation": "babcia",
      "definition": "the mother of one's mother or father",
      "definition_translation": "matka matki lub ojca",
      "example": "My grandmother lives in the countryside.",
      "example_translation": "Moja babcia mieszka na wsi.",
      "imageLink": "https://www.ang.pl/img/slownik/grandmother.jpg",
      "audioLink": "https://www.ang.pl/sound/dict/grandmother.mp3"
    },
    {
      "section": "czlonkowie-rodziny-po-angielsku",
      "language": "English",
      "translationLanguage": "Polish",
      "word": "grandpa",
      "translation": "dziadek",
      "definition": "the father of one's mother or father",
      "definition_translation": "ojciec matki lub ojca",
      "example": "My grandpa lives in the countryside.",
      "example_translation": "Mój dziadek mieszka na wsi.",
      "imageLink": "https://www.ang.pl/img/slownik/grandpa.jpg",
      "audioLink": "https://www.ang.pl/sound/dict/grandpa.mp3"
    },
    {
      "section": "czlonkowie-rodziny-po-angielsku",
      "language": "English",
      "translationLanguage": "Polish",
      "word": "grandparent",
      "translation": "",
      "definition": "",
      "definition_translation": "",
      "example": "",
      "example_translation": "",
      "imageLink": "https://www.ang.pl/img/slownik/grandparent.jpg",
      "audioLink": "https://www.ang.pl/sound/dict/grandparent.mp3"
    },
    {
      "section": "czlonkowie-rodziny-po-angielsku",
      "language": "English",
      "translationLanguage": "Polish",
      "word": "grandparents",
      "translation": "dziadkowie",
      "definition": "the parents of one's father or mother",
      "definition_translation": "rodzice ojca lub matki",
      "example": "I'm going to visit my grandparents next weekend.",
      "example_translation": "Zamierzam odwiedzić moich dziadków w następnym weekendzie.",
      "imageLink": "https://www.ang.pl/img/slownik/grandparents.jpg",
      "audioLink": "https://www.ang.pl/sound/dict/grandparents.mp3"
    },
    {
      "section": "czlonkowie-rodziny-po-angielsku",
      "language": "English",
      "translationLanguage": "Polish",
      "word": "grandson",
      "translation": "wnuk",
      "definition": "a son of one's son or daughter",
      "definition_translation": "syn syna lub córki",
      "example": "My grandson is a very curious boy.",
      "example_translation": "Mój wnuk jest chłopcem bardzo ciekawym.",
      "imageLink": "https://www.ang.pl/img/slownik/grandson.jpg",
      "audioLink": "https://www.ang.pl/sound/dict/grandson.mp3"
    },
    {
      "section": "czlonkowie-rodziny-po-angielsku",
      "language": "English",
      "translationLanguage": "Polish",
      "word": "granny",
      "translation": "babcia",
      "definition": "an old woman, especially one's mother's mother",
      "definition_translation": "stara kobieta, szczególnie babcia",
      "example": "My granny loves baking cookies.",
      "example_translation": "Moja babcia uwielbia piec ciasteczka.",
      "imageLink": "https://www.ang.pl/img/slownik/granny.jpg",
      "audioLink": "https://www.ang.pl/sound/dict/granny.mp3"
    },
    {
      "section": "czlonkowie-rodziny-po-angielsku",
      "language": "English",
      "translationLanguage": "Polish",
      "word": "uncle",
      "translation": "wuj",
      "definition": "The brother of one's mother or father.",
      "definition_translation": "Brat matki lub ojca.",
      "example": "My uncle is a kind man.",
      "example_translation": "Mój wuj jest miłym człowiekiem.",
      "imageLink": "https://www.ang.pl/img/slownik/uncle.jpg",
      "audioLink": "https://www.ang.pl/sound/dict/uncle.mp3"
    },
    {
      "section": "czlonkowie-rodziny-po-angielsku",
      "language": "English",
      "translationLanguage": "Polish",
      "word": "nephew",
      "translation": "siostrzeniec",
      "definition": "the son of your brother or sister",
      "definition_translation": "syn brata lub siostry",
      "example": "My nephew is very clever.",
      "example_translation": "Mój siostrzeniec jest bardzo inteligentny.",
      "imageLink": "https://www.ang.pl/img/slownik/nephew.jpg",
      "audioLink": "https://www.ang.pl/sound/dict/nephew.mp3"
    },
    {
      "section": "czlonkowie-rodziny-po-angielsku",
      "language": "English",
      "translationLanguage": "Polish",
      "word": "niece",
      "translation": "siostrzenica",
      "definition": "The daughter of one's brother or sister, or the daughter of one's spouse's brother or sister.",
      "definition_translation": "Córka brata lub siostry, lub córka brata lub siostry małżonka.",
      "example": "My niece is a clever girl.",
      "example_translation": "Moja siostrzenica to inteligentna dziewczyna.",
      "imageLink": "https://www.ang.pl/img/slownik/niece.jpg",
      "audioLink": "https://www.ang.pl/sound/dict/niece.mp3"
    },
    {
      "section": "czlonkowie-rodziny-po-angielsku",
      "language": "English",
      "translationLanguage": "Polish",
      "word": "relative",
      "translation": "krewny",
      "definition": "a person connected by blood or marriage",
      "definition_translation": "osoba spokrewniona przez krwią lub małżeństwo",
      "example": "My relative is visiting from abroad.",
      "example_translation": "Mój krewny odwiedza nas z zagranicy.",
      "imageLink": "https://www.ang.pl/img/slownik/relative.jpg",
      "audioLink": "https://www.ang.pl/sound/dict/relative.mp3"
    },
    {
      "section": "czlonkowie-rodziny-po-angielsku",
      "language": "English",
      "translationLanguage": "Polish",
      "word": "twin",
      "translation": "",
      "definition": "",
      "definition_translation": "",
      "example": "",
      "example_translation": "",
      "imageLink": "https://www.ang.pl/img/slownik/twin.jpg",
      "audioLink": "https://www.ang.pl/sound/dict/twin.mp3"
    },
    {
      "section": "czlonkowie-rodziny-po-angielsku",
      "language": "English",
      "translationLanguage": "Polish",
      "word": "brother-in-law",
      "translation": "",
      "definition": "",
      "definition_translation": "",
      "example": "",
      "example_translation": "",
      "imageLink": "https://www.ang.pl/img/slownik/brother-in-law.jpg",
      "audioLink": "https://www.ang.pl/sound/dict/brother-in-law.mp3"
    },
    {
      "section": "czlonkowie-rodziny-po-angielsku",
      "language": "English",
      "translationLanguage": "Polish",
      "word": "daughter-in-law",
      "translation": "synowa",
      "definition": "The wife of one's son.",
      "definition_translation": "Żona syna.",
      "example": "My daughter-in-law is a wonderful person.",
      "example_translation": "Moja synowa jest wspaniałą osobą.",
      "imageLink": "https://www.ang.pl/img/slownik/daughter-in-law.jpg",
      "audioLink": "https://www.ang.pl/sound/dict/daughter-in-law.mp3"
    },
    {
      "section": "czlonkowie-rodziny-po-angielsku",
      "language": "English",
      "translationLanguage": "Polish",
      "word": "father-in-law",
      "translation": "teść",
      "definition": "the husband of one's wife or husband",
      "definition_translation": "mąż żony lub męża",
      "example": "My father-in-law is a kind person.",
      "example_translation": "Mój teść jest miłym człowiekiem.",
      "imageLink": "https://www.ang.pl/img/slownik/father-in-law.jpg",
      "audioLink": "https://www.ang.pl/sound/dict/father-in-law.mp3"
    },
    {
      "section": "czlonkowie-rodziny-po-angielsku",
      "language": "English",
      "translationLanguage": "Polish",
      "word": "half-brother",
      "translation": "przybrany brat",
      "definition": "the son of one's mother or father and a different spouse",
      "definition_translation": "syn matki lub ojca i innego małżonka",
      "example": "My half-brother is a doctor.",
      "example_translation": "Mój przybrany brat jest lekarzem.",
      "imageLink": "https://www.ang.pl/img/slownik/half-brother.jpg",
      "audioLink": "https://www.ang.pl/sound/dict/half-brother.mp3"
    },
    {
      "section": "czlonkowie-rodziny-po-angielsku",
      "language": "English",
      "translationLanguage": "Polish",
      "word": "half-sister",
      "translation": "przyrodnia siostra",
      "definition": "The sister of one of your parents, but not your mother or father.",
      "definition_translation": "Siostra jednego z twoich rodziców, ale nie twoja matka lub ojciec.",
      "example": "My half-sister is coming to visit me next week.",
      "example_translation": "Moja przyrodnia siostra przyjedzie do mnie w następnym tygodniu.",
      "imageLink": "https://www.ang.pl/img/slownik/half-sister.jpg",
      "audioLink": "https://www.ang.pl/sound/dict/half-sister.mp3"
    },
    {
      "section": "czlonkowie-rodziny-po-angielsku",
      "language": "English",
      "translationLanguage": "Polish",
      "word": "mother-in-law",
      "translation": "teściowa",
      "definition": "the mother of one's wife or husband",
      "definition_translation": "matka żony lub męża",
      "example": "My mother-in-law is a wonderful person.",
      "example_translation": "Moja teściowa jest wspaniałą osobą.",
      "imageLink": "https://www.ang.pl/img/slownik/mother-in-law.jpg",
      "audioLink": "https://www.ang.pl/sound/dict/mother-in-law.mp3"
    },
    {
      "section": "czlonkowie-rodziny-po-angielsku",
      "language": "English",
      "translationLanguage": "Polish",
      "word": "relations",
      "translation": "relacje",
      "definition": "The way in which two or more people or things are connected",
      "definition_translation": "Sposób, w jaki dwie lub więcej osób lub rzeczy są ze sobą powiązane",
      "example": "The company values its relations with its customers.",
      "example_translation": "Firma ceni relacje ze swoimi klientami.",
      "imageLink": "https://www.ang.pl/img/slownik/relations.jpg",
      "audioLink": "https://www.ang.pl/sound/dict/relations.mp3"
    },
    {
      "section": "czlonkowie-rodziny-po-angielsku",
      "language": "English",
      "translationLanguage": "Polish",
      "word": "siblings",
      "translation": "",
      "definition": "",
      "definition_translation": "",
      "example": "",
      "example_translation": "",
      "imageLink": "https://www.ang.pl/img/slownik/siblings.jpg",
      "audioLink": "https://www.ang.pl/sound/dict/siblings.mp3"
    },
    {
      "section": "czlonkowie-rodziny-po-angielsku",
      "language": "English",
      "translationLanguage": "Polish",
      "word": "sister-in-law",
      "translation": "szwagierka",
      "definition": "the sister of one's husband or wife",
      "definition_translation": "siostra męża lub żony",
      "example": "My sister-in-law is a wonderful person.",
      "example_translation": "Moja szwagierka jest wspaniałą osobą.",
      "imageLink": "https://www.ang.pl/img/slownik/sister-in-law.jpg",
      "audioLink": "https://www.ang.pl/sound/dict/sister-in-law.mp3"
    },
    {
      "section": "czlonkowie-rodziny-po-angielsku",
      "language": "English",
      "translationLanguage": "Polish",
      "word": "son-in-law",
      "translation": "zięć",
      "definition": "The husband of one's daughter.",
      "definition_translation": "Mąż własnej córki.",
      "example": "My son-in-law is a great cook.",
      "example_translation": "Mój zięć jest wielkim kucharzem.",
      "imageLink": "https://www.ang.pl/img/slownik/son-in-law.jpg",
      "audioLink": "https://www.ang.pl/sound/dict/son-in-law.mp3"
    },
    {
      "section": "czlonkowie-rodziny-po-angielsku",
      "language": "English",
      "translationLanguage": "Polish",
      "word": "stepdaughter",
      "translation": "pasierbica",
      "definition": "the daughter of one's husband or wife by a previous marriage",
      "definition_translation": "córka męża lub żony z poprzedniego małżeństwa",
      "example": "She is my stepdaughter from my previous marriage.",
      "example_translation": "Jest to moja pasierbica z poprzedniego małżeństwa.",
      "imageLink": "https://www.ang.pl/img/slownik/stepdaughter.jpg",
      "audioLink": "https://www.ang.pl/sound/dict/stepdaughter.mp3"
    },
    {
      "section": "czlonkowie-rodziny-po-angielsku",
      "language": "English",
      "translationLanguage": "Polish",
      "word": "stepfather",
      "translation": "ojczym",
      "definition": "the husband of one's mother by a subsequent marriage",
      "definition_translation": "mąż matki z następnego małżeństwa",
      "example": "My stepfather is very kind to me.",
      "example_translation": "Mój ojczym jest bardzo miły wobec mnie.",
      "imageLink": "https://www.ang.pl/img/slownik/stepfather.jpg",
      "audioLink": "https://www.ang.pl/sound/dict/stepfather.mp3"
    },
    {
      "section": "czlonkowie-rodziny-po-angielsku",
      "language": "English",
      "translationLanguage": "Polish",
      "word": "stepmother",
      "translation": "macocha",
      "definition": "the mother of one's stepfather or stepmother",
      "definition_translation": "matka ojczyma lub macochy",
      "example": "My stepmother is a kind person.",
      "example_translation": "Moja macocha jest sympatyczną osobą.",
      "imageLink": "https://www.ang.pl/img/slownik/stepmother.jpg",
      "audioLink": "https://www.ang.pl/sound/dict/stepmother.mp3"
    },
    {
      "section": "czlonkowie-rodziny-po-angielsku",
      "language": "English",
      "translationLanguage": "Polish",
      "word": "stepson",
      "translation": "syn ojczyma",
      "definition": "The son of one's husband or wife by a previous marriage.",
      "definition_translation": "Syn męża lub żony z poprzedniego małżeństwa.",
      "example": "My stepson is very friendly.",
      "example_translation": "Mój syn ojczym jest bardzo przyjazny.",
      "imageLink": "https://www.ang.pl/img/slownik/stepson.jpg",
      "audioLink": "https://www.ang.pl/sound/dict/stepson.mp3"
    },
    {
      "section": "czlonkowie-rodziny-po-angielsku",
      "language": "English",
      "translationLanguage": "Polish",
      "word": "spouse",
      "translation": "małżonek",
      "definition": "a person married to another person",
      "definition_translation": "osoba pozostająca w związku małżeńskim z inną osobą",
      "example": "My spouse is a doctor.",
      "example_translation": "Mój małżonek jest doktorem.",
      "imageLink": "https://www.ang.pl/img/slownik/spouse.jpg",
      "audioLink": "https://www.ang.pl/sound/dict/spouse.mp3"
    },
    {
      "section": "czlonkowie-rodziny-po-angielsku",
      "language": "English",
      "translationLanguage": "Polish",
      "word": "in-laws",
      "translation": "teściowie",
      "definition": "the parents of one's spouse",
      "definition_translation": "rodzice współmałżonka",
      "example": "I'm going to visit my in-laws for the holidays.",
      "example_translation": "Zamierzam odwiedzić moich teściów w czasie świąt.",
      "imageLink": "https://www.ang.pl/img/slownik/in-laws.jpg",
      "audioLink": "https://www.ang.pl/sound/dict/in-laws.mp3"
    }
  ]
}