{
  "data": [
    {
      "section": "matematyka-terminy-matematyczne-po-angielsku",
      "language": "Spanish",
      "translationLanguage": "Polish",
      "word": "número",
      "translation": "liczba",
      "definition": "Un número es un valor matemático que se expresa utilizando dígitos.",
      "definition_translation": "Liczba to wartość matematyczna, która wyrażana jest za pomocą cyfr.",
      "example": "El número pi es un número irracional.",
      "example_translation": "Liczba pi jest liczbą niewymierną.",
      "imageLink": "https://www.ang.pl/img/slownik/number.jpg",
      "audioLink": "https://www.ang.pl/sound/dict/number.mp3"
    },
    {
      "section": "matematyka-terminy-matematyczne-po-angielsku",
      "language": "Spanish",
      "translationLanguage": "Polish",
      "word": "círculo",
      "translation": "koło",
      "definition": "Figura geométrica plana y cerrada cuyos puntos equidistan de un centro común.",
      "definition_translation": "Płaska, zamknięta figura geometryczna, której punkty są równoodległe od wspólnego środka.",
      "example": "El niño dibujó un círculo en el pizarra.",
      "example_translation": "Chłopiec narysował koło na tablicy.",
      "imageLink": "https://www.ang.pl/img/slownik/circle-3.jpg",
      "audioLink": "https://www.ang.pl/sound/dict/circle.mp3"
    },
    {
      "section": "matematyka-terminy-matematyczne-po-angielsku",
      "language": "Spanish",
      "translationLanguage": "Polish",
      "word": "cuadrado",
      "translation": "kwadrat",
      "definition": "figura geométrica de cuatro lados iguales",
      "definition_translation": "geometryczna figura o czterech równych bokach",
      "example": "El cuadrado es una figura geométrica básica.",
      "example_translation": "Kwadrat jest geometryczną figurą podstawową.",
      "imageLink": "https://www.ang.pl/img/slownik/square-2.jpg",
      "audioLink": "https://www.ang.pl/sound/dict/square.mp3"
    },
    {
      "section": "matematyka-terminy-matematyczne-po-angielsku",
      "language": "Spanish",
      "translationLanguage": "Polish",
      "word": "estrella",
      "translation": "gwiazda",
      "definition": "Cuerpo celeste que brilla en el cielo nocturno",
      "definition_translation": "Ciało niebieskie, które świeci w nocnym niebie",
      "example": "La estrella más brillante en el cielo es la Luna",
      "example_translation": "Najjaśniejsza gwiazda na niebie to Księżyc",
      "imageLink": "https://www.ang.pl/img/slownik/star-2.jpg",
      "audioLink": "https://www.ang.pl/sound/dict/star.mp3"
    },
    {
      "section": "matematyka-terminy-matematyczne-po-angielsku",
      "language": "Spanish",
      "translationLanguage": "Polish",
      "word": "cross",
      "translation": "krzyż",
      "definition": "signo o figura formada por dos líneas que se cortan en ángulo recto",
      "definition_translation": "znak lub figura utworzona przez dwie linie, które przecinają się pod kątem prostym",
      "example": "La cruz del Norte es una constelación estrellada.",
      "example_translation": "Gwiazda Północna to gwiazdozbiór.",
      "imageLink": "https://www.ang.pl/img/slownik/cross-1.jpg",
      "audioLink": "https://www.ang.pl/sound/dict/cross.mp3"
    },
    {
      "section": "matematyka-terminy-matematyczne-po-angielsku",
      "language": "Spanish",
      "translationLanguage": "Polish",
      "word": "por ciento",
      "translation": "procent",
      "definition": "Una fracción igual a una centésima parte de un todo",
      "definition_translation": "Część równa setnej części całości",
      "example": "El precio del producto es del 20 por ciento más barato que el anterior",
      "example_translation": "Cena produktu jest o 20 procent niższa niż poprzednia",
      "imageLink": "https://www.ang.pl/img/slownik/per-cent.jpg",
      "audioLink": "https://www.ang.pl/sound/dict/per cent.mp3"
    },
    {
      "section": "matematyka-terminy-matematyczne-po-angielsku",
      "language": "Spanish",
      "translationLanguage": "Polish",
      "word": "suma",
      "translation": "suma",
      "definition": "El resultado de agregar dos o más números o cantidades.",
      "definition_translation": "Wynik dodawania dwóch lub więcej liczb lub ilości.",
      "example": "La suma de 2 y 3 es 5.",
      "example_translation": "Suma 2 i 3 to 5.",
      "imageLink": "https://www.ang.pl/img/slownik/sum-1.jpg",
      "audioLink": "https://www.ang.pl/sound/dict/sum.mp3"
    },
    {
      "section": "matematyka-terminy-matematyczne-po-angielsku",
      "language": "Spanish",
      "translationLanguage": "Polish",
      "word": "adición",
      "translation": "dodanie",
      "definition": "Acción de agregar algo a otra cosa",
      "definition_translation": "Czynność dodawania czegoś do czegoś",
      "example": "La adición de un nuevo miembro al equipo mejoró significativamente la productividad.",
      "example_translation": "Dodatek nowego członka do zespołu znacznie poprawił produktywność.",
      "imageLink": "https://www.ang.pl/img/slownik/addition.jpg",
      "audioLink": "https://www.ang.pl/sound/dict/addition.mp3"
    },
    {
      "section": "matematyka-terminy-matematyczne-po-angielsku",
      "language": "Spanish",
      "translationLanguage": "Polish",
      "word": "cono",
      "translation": "stalagmit",
      "definition": "figura geométrica que tiene una base circular y una altura que converge en un punto",
      "definition_translation": "figura geometryczna, która ma bazę okrągłą i wysokość, która łączy się w punkcie",
      "example": "El cono de helado es mi postre favorito",
      "example_translation": "Stalagmit lodowy jest moim ulubionym deserem",
      "imageLink": "https://www.ang.pl/img/slownik/cone-1.jpg",
      "audioLink": "https://www.ang.pl/sound/dict/cone.mp3"
    },
    {
      "section": "matematyka-terminy-matematyczne-po-angielsku",
      "language": "Spanish",
      "translationLanguage": "Polish",
      "word": "cubo",
      "translation": "sześcian",
      "definition": "Un objeto geométrico de seis caras, todas ellas cuadradas.",
      "definition_translation": "Przedmiot geometryczny o sześciu płaszczyznach, wszystkie one kwadratowe.",
      "example": "El cubo de madera es muy pesado.",
      "example_translation": "Sześcian drewniany jest bardzo ciężki.",
      "imageLink": "https://www.ang.pl/img/slownik/cube.jpg",
      "audioLink": "https://www.ang.pl/sound/dict/cube.mp3"
    },
    {
      "section": "matematyka-terminy-matematyczne-po-angielsku",
      "language": "Spanish",
      "translationLanguage": "Polish",
      "word": "diámetro",
      "translation": "średnica",
      "definition": "Distancia que se mide a través del centro de un círculo o una esfera.",
      "definition_translation": "Odległość mierzona przez środek koła lub sfery.",
      "example": "El diámetro de la rueda es de 20 pulgadas.",
      "example_translation": "Średnica koła wynosi 20 cali.",
      "imageLink": "https://www.ang.pl/img/slownik/diameter.jpg",
      "audioLink": "https://www.ang.pl/sound/dict/diameter.mp3"
    },
    {
      "section": "matematyka-terminy-matematyczne-po-angielsku",
      "language": "Spanish",
      "translationLanguage": "Polish",
      "word": "óvalo",
      "translation": "owalny",
      "definition": "De forma de huevo, especialmente en sección transversal.",
      "definition_translation": "W kształcie jajka, szczególnie w przekroju poprzecznym.",
      "example": "La pista de atletismo tiene una forma oval.",
      "example_translation": "Bieżnia lekkoatletyczna ma kształt owalny.",
      "imageLink": "https://www.ang.pl/img/slownik/oval.jpg",
      "audioLink": "https://www.ang.pl/sound/dict/oval.mp3"
    },
    {
      "section": "matematyka-terminy-matematyczne-po-angielsku",
      "language": "Spanish",
      "translationLanguage": "Polish",
      "word": "triángulo",
      "translation": "trójkąt",
      "definition": "Una figura geométrica de tres lados y tres ángulos.",
      "definition_translation": "Figura geometryczna o trzech bokach i trzech kątach.",
      "example": "El triángulo equilátero tiene todos sus lados iguales.",
      "example_translation": "Trójkąt równoboczny ma wszystkie boki równe.",
      "imageLink": "https://www.ang.pl/img/slownik/triangle-1.jpg",
      "audioLink": "https://www.ang.pl/sound/dict/triangle.mp3"
    },
    {
      "section": "matematyka-terminy-matematyczne-po-angielsku",
      "language": "Spanish",
      "translationLanguage": "Polish",
      "word": "ángulo",
      "translation": "kąt",
      "definition": "Figura geométrica formada por dos côtigos que se cortan.",
      "definition_translation": "Figura geometryczna utworzona przez dwa ramiona, które się przecinają.",
      "example": "El ángulo entre las dos calles es muy agudo.",
      "example_translation": "Kąt między dwiema ulicami jest bardzo ostry.",
      "imageLink": "https://www.ang.pl/img/slownik/angle.jpg",
      "audioLink": "https://www.ang.pl/sound/dict/angle.mp3"
    },
    {
      "section": "matematyka-terminy-matematyczne-po-angielsku",
      "language": "Spanish",
      "translationLanguage": "Polish",
      "word": "pirámide",
      "translation": "piramida",
      "definition": "Estructura con base cuadrada y lados triangulares que se van estrechando hasta llegar a la cúspide.",
      "definition_translation": "Struktura z kwadratową bazą i trójkątnymi ścianami, które się zwężają aż do szczytu.",
      "example": "La pirámide de Egipto es una de las siete maravillas del mundo.",
      "example_translation": "Piramida Egiptu jest jedną z siedmiu cudów świata.",
      "imageLink": "https://www.ang.pl/img/slownik/pyramid.jpg",
      "audioLink": "https://www.ang.pl/sound/dict/pyramid.mp3"
    },
    {
      "section": "matematyka-terminy-matematyczne-po-angielsku",
      "language": "Spanish",
      "translationLanguage": "Polish",
      "word": "rectángulo",
      "translation": "prostokąt",
      "definition": "Figura geométrica con cuatro lados, donde todos los ángulos son rectos y los lados opuestos son iguales.",
      "definition_translation": "Figura geometryczna z czterema bokami, gdzie wszystkie kąty są proste, a boki przeciwległe są równe.",
      "example": "El salón de clase tiene un rectángulo de pizarra en la pared.",
      "example_translation": "Sala lekcyjna ma prostokąt tablicy na ścianie.",
      "imageLink": "https://www.ang.pl/img/slownik/rectangle.jpg",
      "audioLink": "https://www.ang.pl/sound/dict/rectangle.mp3"
    },
    {
      "section": "matematyka-terminy-matematyczne-po-angielsku",
      "language": "Spanish",
      "translationLanguage": "Polish",
      "word": "conjunto",
      "translation": "zestaw",
      "definition": "Un conjunto es un grupo de cosas que se consideran juntas.",
      "definition_translation": "Zestaw to grupa rzeczy, które są traktowane razem.",
      "example": "El conjunto de herramientas estaba en la caja.",
      "example_translation": "Zestaw narzędzi był w pudełku.",
      "imageLink": "https://www.ang.pl/img/slownik/set-4.jpg",
      "audioLink": "https://www.ang.pl/sound/dict/set.mp3"
    },
    {
      "section": "matematyka-terminy-matematyczne-po-angielsku",
      "language": "Spanish",
      "translationLanguage": "Polish",
      "word": "variable",
      "translation": "zmienna",
      "definition": "Valor que puede cambiar durante la ejecución de un programa",
      "definition_translation": "Wartość, która może zmieniać się podczas wykonywania programu",
      "example": "La variable x se utiliza para almacenar el resultado de la operación",
      "example_translation": "Zmienna x jest używana do przechowywania wyniku operacji",
      "imageLink": "https://www.ang.pl/img/slownik/variable.jpg",
      "audioLink": "https://www.ang.pl/sound/dict/variable.mp3"
    },
    {
      "section": "matematyka-terminy-matematyczne-po-angielsku",
      "language": "Spanish",
      "translationLanguage": "Polish",
      "word": "ángulo agudo",
      "translation": "ostry kąt",
      "definition": "Un ángulo que mide menos de 90 grados",
      "definition_translation": "Kąt, który mierzy mniej niż 90 stopni",
      "example": "El ángulo agudo forma la base del triangulo",
      "example_translation": "Ostry kąt stanowi bazę trójkąta",
      "imageLink": "https://www.ang.pl/img/slownik/acute-angle.jpg",
      "audioLink": "https://www.ang.pl/sound/dict/acute angle.mp3"
    },
    {
      "section": "matematyka-terminy-matematyczne-po-angielsku",
      "language": "Spanish",
      "translationLanguage": "Polish",
      "word": "eje de coordenadas",
      "translation": "oś współrzędnych",
      "definition": "En geometría, es una línea que se utiliza como referencia para determinar la posición de un punto en un plano.",
      "definition_translation": "W geometrii jest to linia, która służy jako odniesienie do określenia położenia punktu na płaszczyźnie.",
      "example": "El sistema de coordenadas cartesianas tiene tres ejes que se intersectan en un punto llamado origen.",
      "example_translation": "System współrzędnych kartezjańskich ma trzy osie, które przecinają się w punkcie zwany początkiem.",
      "imageLink": "https://www.ang.pl/img/slownik/axis-of-coordinates.jpg",
      "audioLink": "https://www.ang.pl/sound/dict/axis of coordinates.mp3"
    },
    {
      "section": "matematyka-terminy-matematyczne-po-angielsku",
      "language": "Spanish",
      "translationLanguage": "Polish",
      "word": "número cardinal",
      "translation": "liczba kardynalna",
      "definition": "Un número que indica la cantidad de elementos en un conjunto",
      "definition_translation": "Liczba, która wskazuje liczbę elementów w zbiorze",
      "example": "El número cardinal de esta lista es de 5 elementos",
      "example_translation": "Liczba kardynalna tej listy to 5 elementów",
      "imageLink": "https://www.ang.pl/img/slownik/cardinal-number.jpg",
      "audioLink": "https://www.ang.pl/sound/dict/cardinal number.mp3"
    },
    {
      "section": "matematyka-terminy-matematyczne-po-angielsku",
      "language": "Spanish",
      "translationLanguage": "Polish",
      "word": "circunferencia",
      "translation": "obwód",
      "definition": "La distancia alrededor de un círculo o una figura circular.",
      "definition_translation": "Odległość wokół koła lub figury okręgłej.",
      "example": "La circunferencia del círculo es de 20 centímetros.",
      "example_translation": "Obwód koła wynosi 20 centymetrów.",
      "imageLink": "https://www.ang.pl/img/slownik/circumference.jpg",
      "audioLink": "https://www.ang.pl/sound/dict/circumference.mp3"
    },
    {
      "section": "matematyka-terminy-matematyczne-po-angielsku",
      "language": "Spanish",
      "translationLanguage": "Polish",
      "word": "coefficient",
      "translation": "współczynnik",
      "definition": "Un número que indica la relación entre dos cantidades o fenómenos.",
      "definition_translation": "Liczba wskazująca relację między dwoma ilościami lub zjawiskami.",
      "example": "El coefficiente de fricción depende del tipo de superficie.",
      "example_translation": "Współczynnik tarcia zależy od typu powierzchni.",
      "imageLink": "https://www.ang.pl/img/slownik/coefficient.jpg",
      "audioLink": "https://www.ang.pl/sound/dict/coefficient.mp3"
    },
    {
      "section": "matematyka-terminy-matematyczne-po-angielsku",
      "language": "Spanish",
      "translationLanguage": "Polish",
      "word": "brújulas",
      "translation": "kompasy",
      "definition": "Instrumento que indica la dirección, utilizando una aguja magnetizada que señala el norte.",
      "definition_translation": "Narzędzie wskazujące kierunek, używające igły magnetycznej, która wskazuje na północ.",
      "example": "Los navegantes utilizan brújulas paraorientarse en el mar.",
      "example_translation": "Nawigatorzy używają kompasów, aby zorientować się na morzu.",
      "imageLink": "https://www.ang.pl/img/slownik/compasses.jpg",
      "audioLink": "https://www.ang.pl/sound/dict/compasses.mp3"
    },
    {
      "section": "matematyka-terminy-matematyczne-po-angielsku",
      "language": "Spanish",
      "translationLanguage": "Polish",
      "word": "ángulo completo",
      "translation": "pełny kąt",
      "definition": "Un ángulo que comprende 360 grados.",
      "definition_translation": "Kąt, który obejmuje 360 stopni.",
      "example": "El ángulo completo es necesario para cerrar la figura geométrica.",
      "example_translation": "Pełny kąt jest niezbędny, aby zamknąć figurę geometryczną.",
      "imageLink": "https://www.ang.pl/img/slownik/complete-angle.jpg",
      "audioLink": "https://www.ang.pl/sound/dict/complete angle.mp3"
    },
    {
      "section": "matematyka-terminy-matematyczne-po-angielsku",
      "language": "Spanish",
      "translationLanguage": "Polish",
      "word": "sistema de coordenadas",
      "translation": "system współrzędnych",
      "definition": "Un sistema de coordenadas es una herramienta matemática que permite ubicar puntos en el espacio mediante un conjunto de números o coordenadas.",
      "definition_translation": "System współrzędnych to narzędzie matematyczne, które pozwala lokalizować punkty w przestrzeni za pomocą zestawu liczb lub współrzędnych.",
      "example": "En geometría, el sistema de coordenadas cartesiano es utilizado para describir la posición de los objetos en el espacio.",
      "example_translation": "W geometrii system współrzędnych kartezjańskich jest używany do opisu pozycji obiektów w przestrzeni.",
      "imageLink": "https://www.ang.pl/img/slownik/coordinate-system.jpg",
      "audioLink": "https://www.ang.pl/sound/dict/coordinate system.mp3"
    },
    {
      "section": "matematyka-terminy-matematyczne-po-angielsku",
      "language": "Spanish",
      "translationLanguage": "Polish",
      "word": "raíz cúbica",
      "translation": "pierwiastek sześcienny",
      "definition": "Es la raíz tercera de un número, es decir, el valor que elevado al cubo da como resultado ese número.",
      "definition_translation": "To jest trzecia potęga liczby, czyli wartość, która podniesiona do trzeciej potęgi daje wynik tej liczby.",
      "example": "El cubo de 8 es 2, porque 2 es la raíz cúbica de 8.",
      "example_translation": "Sześcian 8 jest równy 2, bo 2 jest pierwiastkiem sześciennym liczby 8.",
      "imageLink": "https://www.ang.pl/img/slownik/cube-root.jpg",
      "audioLink": "https://www.ang.pl/sound/dict/cube root.mp3"
    },
    {
      "section": "matematyka-terminy-matematyczne-po-angielsku",
      "language": "Spanish",
      "translationLanguage": "Polish",
      "word": "cuboid",
      "translation": "bryła",
      "definition": "Figura geométrica tridimensional con doce caras, todas ellas cuadradas.",
      "definition_translation": "Trójwymiarowa figura geometryczna o dwunastu ścianach, wszystkie one są kwadratowe.",
      "example": "El cuboid es una figura común en la arquitectura moderna.",
      "example_translation": "Bryła jest powszechną figurą w architekturze nowoczesnej.",
      "imageLink": "https://www.ang.pl/img/slownik/cuboid.jpg",
      "audioLink": "https://www.ang.pl/sound/dict/cuboid.mp3"
    },
    {
      "section": "matematyka-terminy-matematyczne-po-angielsku",
      "language": "Spanish",
      "translationLanguage": "Polish",
      "word": "cilindro",
      "translation": "cylindry",
      "definition": "Forma geométrica que se genera al girar un rectángulo alrededor de uno de sus lados.",
      "definition_translation": "Forma geometryczna powstająca przez obrót prostokąta wokół jednego z jego boków.",
      "example": "El cilindro es una figura geométrica común en la ingeniería.",
      "example_translation": "Cylindry są wspólną figurą geometryczną w inżynierii.",
      "imageLink": "https://www.ang.pl/img/slownik/cylinder.jpg",
      "audioLink": "https://www.ang.pl/sound/dict/cylinder.mp3"
    },
    {
      "section": "matematyka-terminy-matematyczne-po-angielsku",
      "language": "Spanish",
      "translationLanguage": "Polish",
      "word": "decimal",
      "translation": "dziesiętny",
      "definition": "Sistema de numeración que utiliza 10 dígitos, de 0 a 9, para representar cantidades.",
      "definition_translation": "System dziesiętny, który używa 10 cyfr, od 0 do 9, aby reprezentować ilości.",
      "example": "El número 10.25 es un número decimal.",
      "example_translation": "Liczba 10.25 jest liczbą dziesiętną.",
      "imageLink": "https://www.ang.pl/img/slownik/decimal.jpg",
      "audioLink": "https://www.ang.pl/sound/dict/decimal.mp3"
    },
    {
      "section": "matematyka-terminy-matematyczne-po-angielsku",
      "language": "Spanish",
      "translationLanguage": "Polish",
      "word": "ecuación diferencial",
      "translation": "równanie różniczkowe",
      "definition": "Una ecuación diferencial es una ecuación que relaciona una función con sus derivadas.",
      "definition_translation": "Równanie różniczkowe jest równaniem, które łączy funkcję z jej pochodnymi.",
      "example": "La ecuación diferencial más simple es la ecuación lineal de primer orden.",
      "example_translation": "Najprostsze równanie różniczkowe jest liniowym równaniem pierwszego rzędu.",
      "imageLink": "https://www.ang.pl/img/slownik/differential-equation.jpg",
      "audioLink": "https://www.ang.pl/sound/dict/differential equation.mp3"
    },
    {
      "section": "matematyka-terminy-matematyczne-po-angielsku",
      "language": "Spanish",
      "translationLanguage": "Polish",
      "word": "digit",
      "translation": "cyfra",
      "definition": "Un símbolo o carácter que representa un número o una cantidad.",
      "definition_translation": "Symbol lub caratter, który reprezentuje liczbę lub ilość.",
      "example": "El código de verificación está compuesto por 5 dígitos.",
      "example_translation": "Kod weryfikacyjny składa się z 5 cyfr.",
      "imageLink": "https://www.ang.pl/img/slownik/digit.jpg",
      "audioLink": "https://www.ang.pl/sound/dict/digit.mp3"
    },
    {
      "section": "matematyka-terminy-matematyczne-po-angielsku",
      "language": "Spanish",
      "translationLanguage": "Polish",
      "word": "dividendo",
      "translation": "działka",
      "definition": "Cada una de las partes en que se divide una cosa o un conjunto",
      "definition_translation": "Każda z części, na które coś lub zestaw dzieli się",
      "example": "El dividendo de la empresa se pagará en dos meses.",
      "example_translation": "Dywidenda spółki zostanie wypłacona w ciągu dwóch miesięcy.",
      "imageLink": "https://www.ang.pl/img/slownik/divident.jpg",
      "audioLink": "https://www.ang.pl/sound/dict/divident.mp3"
    },
    {
      "section": "matematyka-terminy-matematyczne-po-angielsku",
      "language": "Spanish",
      "translationLanguage": "Polish",
      "word": "división",
      "translation": "podział",
      "definition": "Acción y efecto de dividir o separar algo en partes.",
      "definition_translation": "Czynność i efekt dzielenia lub rozdzielania czegoś na części.",
      "example": "La división de la empresa en departamentos ha mejorado la eficiencia.",
      "example_translation": "Podział firmy na departamenty poprawił wydajność.",
      "imageLink": "https://www.ang.pl/img/slownik/division.jpg",
      "audioLink": "https://www.ang.pl/sound/dict/division.mp3"
    },
    {
      "section": "matematyka-terminy-matematyczne-po-angielsku",
      "language": "Spanish",
      "translationLanguage": "Polish",
      "word": "divisor",
      "translation": "dzielnik",
      "definition": "Cada uno de los números que se utilizan para dividir a otros números.",
      "definition_translation": "Każdy z liczb używanych do dzielenia innych liczb.",
      "example": "El número 2 es un divisor del número 10.",
      "example_translation": "Liczba 2 jest dzielnikiem liczby 10.",
      "imageLink": "https://www.ang.pl/img/slownik/divisor.jpg",
      "audioLink": "https://www.ang.pl/sound/dict/divisor.mp3"
    },
    {
      "section": "matematyka-terminy-matematyczne-po-angielsku",
      "language": "Spanish",
      "translationLanguage": "Polish",
      "word": "exponente, potencia",
      "translation": "wykładnik, potęga",
      "definition": "Un exponente o potencia es un número que indica cuántas veces debe multiplicarse una base para obtener un resultado.",
      "definition_translation": "Wyrobnik lub potęga to liczba, która wskazuje, ile razy należy pomnożyć podstawę, aby uzyskać wynik.",
      "example": "El exponente 2 en la expresión 2³ indica que la base 2 se eleva al cubo.",
      "example_translation": "Wyrobnik 2 w wyrażeniu 2³ oznacza, że podstawa 2 jest podniesiona do sześcianu.",
      "imageLink": "https://www.ang.pl/img/slownik/exponent-power.jpg",
      "audioLink": "https://www.ang.pl/sound/dict/exponent, power.mp3"
    },
    {
      "section": "matematyka-terminy-matematyczne-po-angielsku",
      "language": "Spanish",
      "translationLanguage": "Polish",
      "word": "fracción",
      "translation": "'ułamek",
      "definition": "Parte de un todo, especialmente en matemáticas.",
      "definition_translation": "Część całości, szczególnie w matematyce.",
      "example": "La fracción de los estudiantes que aprobaron el examen fue del 80%.",
      "example_translation": "Ułamek studentów, którzy zdali egzamin, wynosił 80%.",
      "imageLink": "https://www.ang.pl/img/slownik/fraction.jpg",
      "audioLink": "https://www.ang.pl/sound/dict/fraction.mp3"
    },
    {
      "section": "matematyka-terminy-matematyczne-po-angielsku",
      "language": "Spanish",
      "translationLanguage": "Polish",
      "word": "función",
      "translation": "funkcja",
      "definition": "Una función es un bloque de código que se puede ejecutar varias veces desde diferentes partes de un programa.",
      "definition_translation": "Funkcja to blok kodu, który może być wykonywany wielokrotnie z różnych części programu.",
      "example": "La función calcularArea calcula el área de un triángulo.",
      "example_translation": "Funkcja obliczaniePola oblicza pole trójkąta.",
      "imageLink": "https://www.ang.pl/img/slownik/function.jpg",
      "audioLink": "https://www.ang.pl/sound/dict/function.mp3"
    },
    {
      "section": "matematyka-terminy-matematyczne-po-angielsku",
      "language": "Spanish",
      "translationLanguage": "Polish",
      "word": "hemisferio",
      "translation": "półkula",
      "definition": "Cada una de las dos mitades en que se divide la Tierra o el cielo, separadas por un plano que pasa por el centro del globo.",
      "definition_translation": "Każda z dwóch połówek, na które dzieli się Ziemia lub niebo, oddzielone płaszczyzną przechodzącą przez środek globu.",
      "example": "El hemisferio norte es la región del planeta más poblada.",
      "example_translation": "Półkula północna jest najbardziej zaludnionym regionem na Ziemi.",
      "imageLink": "https://www.ang.pl/img/slownik/hemisphere.jpg",
      "audioLink": "https://www.ang.pl/sound/dict/hemisphere.mp3"
    },
    {
      "section": "matematyka-terminy-matematyczne-po-angielsku",
      "language": "Spanish",
      "translationLanguage": "Polish",
      "word": "heptágono",
      "translation": "siedmiokąt",
      "definition": "Polígono de siete lados",
      "definition_translation": "Wielokąt o siedmiu bokach",
      "example": "El heptágono es una figura geométrica común en la naturaleza.",
      "example_translation": "Siedmiokąt jest wspólną figurą geometryczną w naturze.",
      "imageLink": "https://www.ang.pl/img/slownik/heptagon.jpg",
      "audioLink": "https://www.ang.pl/sound/dict/heptagon.mp3"
    },
    {
      "section": "matematyka-terminy-matematyczne-po-angielsku",
      "language": "Spanish",
      "translationLanguage": "Polish",
      "word": "hexágono",
      "translation": "sześcian",
      "definition": "Polígono de seis lados",
      "definition_translation": "Wielokąt o sześciu bokach",
      "example": "El hexágono es una figura geométrica común en la naturaleza.",
      "example_translation": "Sześcian jest common figurą geometryczną w naturze.",
      "imageLink": "https://www.ang.pl/img/slownik/hexagon.jpg",
      "audioLink": "https://www.ang.pl/sound/dict/hexagon.mp3"
    },
    {
      "section": "matematyka-terminy-matematyczne-po-angielsku",
      "language": "Spanish",
      "translationLanguage": "Polish",
      "word": "infinito",
      "translation": "nieskończoność",
      "definition": "Cantidad ilimitada o sin fin en cantidad, número o duración.",
      "definition_translation": "Nieograniczona lub bez końca ilość, liczba lub trwanie.",
      "example": "El universo tiene un tamaño infinito.",
      "example_translation": "Wszechświat ma nieskończoną wielkość.",
      "imageLink": "https://www.ang.pl/img/slownik/infinity.jpg",
      "audioLink": "https://www.ang.pl/sound/dict/infinity.mp3"
    },
    {
      "section": "matematyka-terminy-matematyczne-po-angielsku",
      "language": "Spanish",
      "translationLanguage": "Polish",
      "word": "entero",
      "translation": "całkowita",
      "definition": "Número que no tiene decimales.",
      "definition_translation": "Liczba, która nie ma cyfr po przecinku.",
      "example": "El entero 5 es un número primo.",
      "example_translation": "Całkowita 5 jest liczbą pierwszą.",
      "imageLink": "https://www.ang.pl/img/slownik/integer.jpg",
      "audioLink": "https://www.ang.pl/sound/dict/integer.mp3"
    },
    {
      "section": "matematyka-terminy-matematyczne-po-angielsku",
      "language": "Spanish",
      "translationLanguage": "Polish",
      "word": "integral",
      "translation": "całkowity",
      "definition": "Que forma una unidad completa o total",
      "definition_translation": "Który tworzy kompletne lub całkowite jednostki",
      "example": "El objetivo es alcanzar una visión integral del proyecto.",
      "example_translation": "Celem jest uzyskanie kompleksowego widoku projektu.",
      "imageLink": "https://www.ang.pl/img/slownik/integral.jpg",
      "audioLink": "https://www.ang.pl/sound/dict/integral.mp3"
    },
    {
      "section": "matematyka-terminy-matematyczne-po-angielsku",
      "language": "Spanish",
      "translationLanguage": "Polish",
      "word": "número irracional",
      "translation": "liczba niewymierna",
      "definition": "Un número que no puede ser expresado como una relación de dos números enteros.",
      "definition_translation": "Liczba, która nie może być wyrażona jako stosunek dwóch liczb całkowitych.",
      "example": "El número pi es un ejemplo de número irracional.",
      "example_translation": "Liczba pi jest przykładem liczby niewymiernej.",
      "imageLink": "https://www.ang.pl/img/slownik/irrational-number.jpg",
      "audioLink": "https://www.ang.pl/sound/dict/irrational number.mp3"
    },
    {
      "section": "matematyka-terminy-matematyczne-po-angielsku",
      "language": "Spanish",
      "translationLanguage": "Polish",
      "word": "segmento de línea",
      "translation": "odbicie odcinka",
      "definition": "Parte de una línea que se encuentra entre dos puntos determinados.",
      "definition_translation": "Część linii znajdująca się między dwoma określonymi punktami.",
      "example": "El segmento de línea AB es perpendicular al plano XYZ.",
      "example_translation": "Odcinek linii AB jest prostopadły do płaszczyzny XYZ.",
      "imageLink": "https://www.ang.pl/img/slownik/line-segment.jpg",
      "audioLink": "https://www.ang.pl/sound/dict/line segment.mp3"
    },
    {
      "section": "matematyka-terminy-matematyczne-po-angielsku",
      "language": "Spanish",
      "translationLanguage": "Polish",
      "word": "logaritmo",
      "translation": "logarytm",
      "definition": " El logaritmo es una función matemática que permite encontrar el exponente al que debe ser elevada una base para producir un número dado.",
      "definition_translation": "Logarytm jest funkcją matematyczną, która pozwala znaleźć wykładnik, do którego należy podnieść podstawę, aby uzyskać dane liczbowe.",
      "example": "El logaritmo natural de 100 es 2, ya que 100 es igual a e elevado a la potencia de 2.",
      "example_translation": "Logarytm naturalny z 100 jest równy 2, ponieważ 100 jest równe e podniesionemu do potęgi 2.",
      "imageLink": "https://www.ang.pl/img/slownik/logarithm.jpg",
      "audioLink": "https://www.ang.pl/sound/dict/logarithm.mp3"
    },
    {
      "section": "matematyka-terminy-matematyczne-po-angielsku",
      "language": "Spanish",
      "translationLanguage": "Polish",
      "word": "multiplicación",
      "translation": "mnożenie",
      "definition": "Acción de multiplicar algo",
      "definition_translation": "Czynność mnożenia czegoś",
      "example": "La multiplicación de 2 por 3 es igual a 6",
      "example_translation": "Mnożenie 2 przez 3 jest równe 6",
      "imageLink": "https://www.ang.pl/img/slownik/multiplication.jpg",
      "audioLink": "https://www.ang.pl/sound/dict/multiplication.mp3"
    },
    {
      "section": "matematyka-terminy-matematyczne-po-angielsku",
      "language": "Spanish",
      "translationLanguage": "Polish",
      "word": "natural number",
      "translation": "liczba naturalna",
      "definition": "Un número entero positivo, es decir, un número que se puede expresar sin utilizar números negativos ni decimales.",
      "definition_translation": "Dodatnia liczba całkowita, czyli liczba, która może być wyrażona bez używania liczb ujemnych ani dziesiętnych.",
      "example": "El conjunto de los números naturales es infinito.",
      "example_translation": "Zbiór liczb naturalnych jest nieskończony.",
      "imageLink": "https://www.ang.pl/img/slownik/natural-number.jpg",
      "audioLink": "https://www.ang.pl/sound/dict/natural number.mp3"
    },
    {
      "section": "matematyka-terminy-matematyczne-po-angielsku",
      "language": "Spanish",
      "translationLanguage": "Polish",
      "word": "number line",
      "translation": "linia liczb",
      "definition": "Una línea que muestra los números en orden creciente o decreciente.",
      "definition_translation": "Linia, która pokazuje liczby w kolejności rosnącej lub malejącej.",
      "example": "Los niños utilizan la línea de números para sumar y restar.",
      "example_translation": "Dzieci używają linii liczb, aby dodać i odejmować.",
      "imageLink": "https://www.ang.pl/img/slownik/number-line.jpg",
      "audioLink": "https://www.ang.pl/sound/dict/number line.mp3"
    },
    {
      "section": "matematyka-terminy-matematyczne-po-angielsku",
      "language": "Spanish",
      "translationLanguage": "Polish",
      "word": "ángulo obtuso",
      "translation": "kąt tępy",
      "definition": "Un ángulo obtuso es un ángulo que mide más de 90 grados.",
      "definition_translation": "Kąt tępy to kąt, który mierzy więcej niż 90 stopni.",
      "example": "El ángulo obtuso forma parte de la figura geométrica.",
      "example_translation": "Kąt tępy jest częścią figury geometrycznej.",
      "imageLink": "https://www.ang.pl/img/slownik/obtuse-angle.jpg",
      "audioLink": "https://www.ang.pl/sound/dict/obtuse angle.mp3"
    },
    {
      "section": "matematyka-terminy-matematyczne-po-angielsku",
      "language": "Spanish",
      "translationLanguage": "Polish",
      "word": "octágono",
      "translation": "ośmiokąt",
      "definition": "Polígono de ocho lados",
      "definition_translation": "Wielokąt o ośmiu stronach",
      "example": "El octágono es una figura geométrica común en la arquitectura",
      "example_translation": "Ośmiokąt jest wspólną figurą geometryczną w architekturze",
      "imageLink": "https://www.ang.pl/img/slownik/octagon.jpg",
      "audioLink": "https://www.ang.pl/sound/dict/octagon.mp3"
    },
    {
      "section": "matematyka-terminy-matematyczne-po-angielsku",
      "language": "Spanish",
      "translationLanguage": "Polish",
      "word": "número ordinal",
      "translation": "liczba porządkowa",
      "definition": "Un número que expresa la posición o orden de algo en una serie.",
      "definition_translation": "Liczba, która wyraża pozycję lub kolejność czegoś w serii.",
      "example": "El número ordinal de esta carta es tercero.",
      "example_translation": "Liczba porządkowa tej karty to trzecie.",
      "imageLink": "https://www.ang.pl/img/slownik/ordinal-number.jpg",
      "audioLink": "https://www.ang.pl/sound/dict/ordinal number.mp3"
    },
    {
      "section": "matematyka-terminy-matematyczne-po-angielsku",
      "language": "Spanish",
      "translationLanguage": "Polish",
      "word": "paralelo",
      "translation": "równoległy",
      "definition": "Dicho de dos o más cosas: Que tienen la misma dirección y nunca se cruzan.",
      "definition_translation": "Powiedziane o dwóch lub więcej rzeczach: Mających tę samą kierunek i nigdy nie krzyżujących się.",
      "example": "Los dos caminos eran paralelos y nunca se cruzaban.",
      "example_translation": "Oba drogi były równoległe i nigdy się nie krzyżowały.",
      "imageLink": "https://www.ang.pl/img/slownik/parallel.jpg",
      "audioLink": "https://www.ang.pl/sound/dict/parallel.mp3"
    },
    {
      "section": "matematyka-terminy-matematyczne-po-angielsku",
      "language": "Spanish",
      "translationLanguage": "Polish",
      "word": "paralelogramo",
      "translation": "paralelogram",
      "definition": "Figura geométrica cuadrilateral cuyos lados opuestos son paralelos.",
      "definition_translation": "Czworokąt geometryczny, którego przeciwległe boki są równoległe.",
      "example": "El paralelogramo es una figura geométrica común en la naturaleza.",
      "example_translation": "Paralelogram jest common geometryczną figurą w naturze.",
      "imageLink": "https://www.ang.pl/img/slownik/parallelogram.jpg",
      "audioLink": "https://www.ang.pl/sound/dict/parallelogram.mp3"
    },
    {
      "section": "matematyka-terminy-matematyczne-po-angielsku",
      "language": "Spanish",
      "translationLanguage": "Polish",
      "word": "pentágono",
      "translation": "pięciokąt",
      "definition": "Polígono de cinco lados",
      "definition_translation": "Wielokąt o pięciu bokach",
      "example": "El pentágono es una figura geométrica común en la arquitectura",
      "example_translation": "Pięciokąt jest powszechną figurą geometryczną w architekturze",
      "imageLink": "https://www.ang.pl/img/slownik/pentagon.jpg",
      "audioLink": "https://www.ang.pl/sound/dict/pentagon.mp3"
    },
    {
      "section": "matematyka-terminy-matematyczne-po-angielsku",
      "language": "Spanish",
      "translationLanguage": "Polish",
      "word": "perpendicular",
      "translation": "prostopadły",
      "definition": "Línea o plano que forma ángulo recto con otra línea o plano.",
      "definition_translation": "Linia lub płaszczyzna, która tworzy kąt prosty z inną linią lub płaszczyzną.",
      "example": "La línea perpendicular al suelo forma un ángulo de 90 grados.",
      "example_translation": "Linia prostopadła do podłogi tworzy kąt 90 stopni.",
      "imageLink": "https://www.ang.pl/img/slownik/perpendicular.jpg",
      "audioLink": "https://www.ang.pl/sound/dict/perpendicular.mp3"
    },
    {
      "section": "matematyka-terminy-matematyczne-po-angielsku",
      "language": "Spanish",
      "translationLanguage": "Polish",
      "word": "número primo",
      "translation": "liczba pierwsza",
      "definition": "Un número natural mayor que 1 que no tiene divisores enteros positivos excepto 1 y sí mismo.",
      "definition_translation": "Liczbę naturalną większą niż 1, która nie ma dzielników całkowitych dodatnich poza 1 i sama sobą.",
      "example": "El número 7 es un número primo porque solo es divisible entre 1 y 7.",
      "example_translation": "Liczba 7 jest liczbą pierwszą, ponieważ jest podzielna tylko przez 1 i 7.",
      "imageLink": "https://www.ang.pl/img/slownik/prime-number.jpg",
      "audioLink": "https://www.ang.pl/sound/dict/prime number.mp3"
    },
    {
      "section": "matematyka-terminy-matematyczne-po-angielsku",
      "language": "Spanish",
      "translationLanguage": "Polish",
      "word": "prisma",
      "translation": "pryzma",
      "definition": "Un prisma es un sólido geométrico que tiene bases poligonales y lados rectangulares.",
      "definition_translation": " Pryzma to bryła geometryczna, która ma poligonalne podstawy i proste ściany boczne.",
      "example": "El prisma de cristal refractó la luz de manera interesante.",
      "example_translation": "Pryzma kryształowa odbiła światło w interesujący sposób.",
      "imageLink": "https://www.ang.pl/img/slownik/prism.jpg",
      "audioLink": "https://www.ang.pl/sound/dict/prism.mp3"
    },
    {
      "section": "matematyka-terminy-matematyczne-po-angielsku",
      "language": "Spanish",
      "translationLanguage": "Polish",
      "word": "producto",
      "translation": "produkt",
      "definition": "Una cosa fabricada o vendida",
      "definition_translation": "Rzecz wyprodukowana lub sprzedawana",
      "example": "El producto es de alta calidad.",
      "example_translation": "Produkt jest wysokiej jakości.",
      "imageLink": "https://www.ang.pl/img/slownik/product-1.jpg",
      "audioLink": "https://www.ang.pl/sound/dict/product.mp3"
    },
    {
      "section": "matematyka-terminy-matematyczne-po-angielsku",
      "language": "Spanish",
      "translationLanguage": "Polish",
      "word": "Teorema de Pitágoras",
      "translation": "Twierdzenie Pitagorasa",
      "definition": "El teorema de Pitágoras es un teorema fundamental en geometría que establece la relación entre los lados de un triángulo rectángulo.",
      "definition_translation": "Twierdzenie Pitagorasa to fundamentalne twierdzenie w geometrii, które określa relację między bokami trójkąta prostokątnego.",
      "example": "El teorema de Pitágoras se utiliza para calcular la longitud de la hipotenusa de un triángulo rectángulo.",
      "example_translation": "Twierdzenie Pitagorasa służy do obliczania długości przeciwprostokątnej trójkąta prostokątnego.",
      "imageLink": "https://www.ang.pl/img/slownik/pythagorean-theorem.jpg",
      "audioLink": "https://www.ang.pl/sound/dict/Pythagorean theorem.mp3"
    },
    {
      "section": "matematyka-terminy-matematyczne-po-angielsku",
      "language": "Spanish",
      "translationLanguage": "Polish",
      "word": "ecuación cuadrática",
      "translation": "równanie kwadratowe",
      "definition": "Una ecuación cuadrática es una ecuación algebraica de segundo grado, es decir, una ecuación de la forma ax^2 + bx + c = 0, donde a, b y c son números reales y x es la incógnita.",
      "definition_translation": "Równanie kwadratowe to równanie algebraiczne drugiego stopnia, czyli równanie postaci ax^2 + bx + c = 0, gdzie a, b i c są liczbami rzeczywistymi, a x jest niewiadomą.",
      "example": "La ecuación cuadrática x^2 + 4x + 4 = 0 tiene dos soluciones: x = -2 y x = -2.",
      "example_translation": "Równanie kwadratowe x^2 + 4x + 4 = 0 ma dwie rozwiązania: x = -2 oraz x = -2.",
      "imageLink": "https://www.ang.pl/img/slownik/quadratic-equation.jpg",
      "audioLink": "https://www.ang.pl/sound/dict/quadratic equation.mp3"
    },
    {
      "section": "matematyka-terminy-matematyczne-po-angielsku",
      "language": "Spanish",
      "translationLanguage": "Polish",
      "word": "cociente",
      "translation": "iloczyn",
      "definition": "El resultado de dividir un número entre otro.",
      "definition_translation": "Wynik dzielenia jednej liczby przez inną.",
      "example": "El cociente de 10 entre 2 es 5.",
      "example_translation": "Iloczyn 10 przez 2 jest równy 5.",
      "imageLink": "https://www.ang.pl/img/slownik/quotient.jpg",
      "audioLink": "https://www.ang.pl/sound/dict/quotient.mp3"
    },
    {
      "section": "matematyka-terminy-matematyczne-po-angielsku",
      "language": "Spanish",
      "translationLanguage": "Polish",
      "word": "radio",
      "translation": "promień",
      "definition": "distancia desde el centro de un círculo o esfera hasta su perímetro o superficie",
      "definition_translation": "odległość od środka koła lub sfery do jego obwodu lub powierzchni",
      "example": "El radio de la Tierra es de aproximadamente 6.371 kilómetros.",
      "example_translation": "Promień Ziemi wynosi około 6 371 kilometrów.",
      "imageLink": "https://www.ang.pl/img/slownik/radius.jpg",
      "audioLink": "https://www.ang.pl/sound/dict/radius.mp3"
    },
    {
      "section": "matematyka-terminy-matematyczne-po-angielsku",
      "language": "Spanish",
      "translationLanguage": "Polish",
      "word": "número racional",
      "translation": "liczba rzeczowa",
      "definition": "Un número racional es un número que puede ser expresado como la relación entre dos números enteros.",
      "definition_translation": "Liczba rzeczowa to liczba, która może być wyrażona jako relacja dwóch liczb całkowitych.",
      "example": "El número π no es un número racional.",
      "example_translation": "Liczba π nie jest liczbą rzeczową.",
      "imageLink": "https://www.ang.pl/img/slownik/rational-number.jpg",
      "audioLink": "https://www.ang.pl/sound/dict/rational number.mp3"
    },
    {
      "section": "matematyka-terminy-matematyczne-po-angielsku",
      "language": "Spanish",
      "translationLanguage": "Polish",
      "word": "número real",
      "translation": "liczba rzeczywista",
      "definition": "Un número real es un número que puede ser expresado como un decimal o fracción.",
      "definition_translation": "Liczba rzeczywista to liczba, która może być wyrażona jako dziesiętna lub ułamkowa.",
      "example": "El número pi es un número real irracional.",
      "example_translation": "Liczba pi jest liczbą rzeczywistą niewymierną.",
      "imageLink": "https://www.ang.pl/img/slownik/real-number.jpg",
      "audioLink": "https://www.ang.pl/sound/dict/real number.mp3"
    },
    {
      "section": "matematyka-terminy-matematyczne-po-angielsku",
      "language": "Spanish",
      "translationLanguage": "Polish",
      "word": "ángulo de reflexión",
      "translation": "kąt odbicia",
      "definition": "El ángulo formado por la dirección de un rayo incidente y la dirección del rayo reflectado.",
      "definition_translation": "Kąt utworzony przez kierunek pada promienia i kierunek promienia odbitego.",
      "example": "El ángulo de reflexión es igual al ángulo de incidencia en una superficie plana.",
      "example_translation": "Kąt odbicia jest równy kątowi padającemu na płaskiej powierzchni.",
      "imageLink": "https://www.ang.pl/img/slownik/reflex-angle.jpg",
      "audioLink": "https://www.ang.pl/sound/dict/reflex angle.mp3"
    },
    {
      "section": "matematyka-terminy-matematyczne-po-angielsku",
      "language": "Spanish",
      "translationLanguage": "Polish",
      "word": "rombo",
      "translation": "różnie się",
      "definition": "Figura geométrica con cuatro lados iguales, opuestos dos a dos, y ángulos internos que suman 360 grados.",
      "definition_translation": "Czworokąt o równych bokach, przeciwległych dwóch dwóch, i kątach wewnętrznych sumujących 360 stopni.",
      "example": "El rombo es un tipo de cuadrilátero con propiedades interesantes.",
      "example_translation": "Różnie się to jeden z rodzajów czworokąta o interesujących właściwościach.",
      "imageLink": "https://www.ang.pl/img/slownik/rhombus.jpg",
      "audioLink": "https://www.ang.pl/sound/dict/rhombus.mp3"
    },
    {
      "section": "matematyka-terminy-matematyczne-po-angielsku",
      "language": "Spanish",
      "translationLanguage": "Polish",
      "word": "ángulo recto",
      "translation": "kąt prosty",
      "definition": "Un ángulo recto es un ángulo que mide 90 grados.",
      "definition_translation": "Kąt prosty to kąt, który mierzy 90 stopni.",
      "example": "El carro se detuvo en un ángulo recto en la intersección.",
      "example_translation": "Samochód zatrzymał się pod kątem prostym na skrzyżowaniu.",
      "imageLink": "https://www.ang.pl/img/slownik/right-angle.jpg",
      "audioLink": "https://www.ang.pl/sound/dict/right angle.mp3"
    },
    {
      "section": "matematyka-terminy-matematyczne-po-angielsku",
      "language": "Spanish",
      "translationLanguage": "Polish",
      "word": "raíz",
      "translation": "korzeń",
      "definition": "Parte de una planta que crece bajo tierra",
      "definition_translation": "Część rośliny, która rośnie pod ziemią",
      "example": "La raíz de la planta era muy profunda.",
      "example_translation": "Korzeń rośliny był bardzo głęboki.",
      "imageLink": "https://www.ang.pl/img/slownik/root-1.jpg",
      "audioLink": "https://www.ang.pl/sound/dict/root.mp3"
    },
    {
      "section": "matematyka-terminy-matematyczne-po-angielsku",
      "language": "Spanish",
      "translationLanguage": "Polish",
      "word": "esfera",
      "translation": "sféra",
      "definition": "Figura geométrica tridimensional que se genera al girar un círculo alrededor de su diámetro.",
      "definition_translation": "Trójwymiarowa figura geometryczna powstająca przez obrót koła wokół jego średnicy.",
      "example": "La Tierra es un ejemplo de una esfera.",
      "example_translation": "Ziemia jest przykładem sfery.",
      "imageLink": "https://www.ang.pl/img/slownik/sphere.jpg",
      "audioLink": "https://www.ang.pl/sound/dict/sphere.mp3"
    },
    {
      "section": "matematyka-terminy-matematyczne-po-angielsku",
      "language": "Spanish",
      "translationLanguage": "Polish",
      "word": "raíz cuadrada",
      "translation": "pierwiastek kwadratowy",
      "definition": "El valor que, al ser elevado al cuadrado, da como resultado un número determinado.",
      "definition_translation": "Wartość, która, podniesiona do kwadratu, daje wynik określonej liczby.",
      "example": "La raíz cuadrada de 16 es 4.",
      "example_translation": "Pierwiastek kwadratowy z 16 jest równy 4.",
      "imageLink": "https://www.ang.pl/img/slownik/square-root.jpg",
      "audioLink": "https://www.ang.pl/sound/dict/square root.mp3"
    },
    {
      "section": "matematyka-terminy-matematyczne-po-angielsku",
      "language": "Spanish",
      "translationLanguage": "Polish",
      "word": "ángulo recto",
      "translation": "kąt prosty",
      "definition": "Un ángulo que tiene 90 grados.",
      "definition_translation": "Kąt, którego miara wynosi 90 stopni.",
      "example": "En la figura, los ángulos rectos se encuentran en las esquinas del cuadrado.",
      "example_translation": "Na rysunku, kąty proste znajdują się w narożnikach kwadratu.",
      "imageLink": "https://www.ang.pl/img/slownik/straight-angle.jpg",
      "audioLink": "https://www.ang.pl/sound/dict/straight angle.mp3"
    },
    {
      "section": "matematyka-terminy-matematyczne-po-angielsku",
      "language": "Spanish",
      "translationLanguage": "Polish",
      "word": "subconjunto",
      "translation": "podzbiór",
      "definition": "Parte de un conjunto que también es un conjunto",
      "definition_translation": "Część zbioru, która również jest zbiorem",
      "example": "El subconjunto de los números primos es infinito.",
      "example_translation": "Podzbiór liczb pierwszych jest nieskończony.",
      "imageLink": "https://www.ang.pl/img/slownik/subset.jpg",
      "audioLink": "https://www.ang.pl/sound/dict/subset.mp3"
    },
    {
      "section": "matematyka-terminy-matematyczne-po-angielsku",
      "language": "Spanish",
      "translationLanguage": "Polish",
      "word": "subtraction",
      "translation": "odjęcie",
      "definition": "La acción de restar una cantidad a otra",
      "definition_translation": "Czynność odejmowania jednej liczby od drugiej",
      "example": "La subtraction es una operación matemática fundamental",
      "example_translation": "Odejście jest podstawową operacją matematyczną",
      "imageLink": "https://www.ang.pl/img/slownik/subtraction.jpg",
      "audioLink": "https://www.ang.pl/sound/dict/subtraction.mp3"
    },
    {
      "section": "matematyka-terminy-matematyczne-po-angielsku",
      "language": "Spanish",
      "translationLanguage": "Polish",
      "word": "Teorema de Tales",
      "translation": "Twierdzenie Talesa",
      "definition": "Un teorema que describe la relación entre la circunferencia de un círculo y una corda que la intersecta",
      "definition_translation": "Twierdzenie opisujące relację pomiędzy okręgiem koła a cięciwą, która ją przecina",
      "example": "El teorema de Tales se aplica en geometría para encontrar la longitud de una corda en un círculo",
      "example_translation": "Twierdzenie Talesa stosuje się w geometrii, aby znaleźć długość cięciwy w kole",
      "imageLink": "https://www.ang.pl/img/slownik/thales-theorem.jpg",
      "audioLink": "https://www.ang.pl/sound/dict/Thales' theorem.mp3"
    },
    {
      "section": "matematyka-terminy-matematyczne-po-angielsku",
      "language": "Spanish",
      "translationLanguage": "Polish",
      "word": "torus",
      "translation": "torus",
      "definition": " figura geométrica formada por una curva cerrada que se cierra sobre sí misma",
      "definition_translation": "figura geometryczna utworzona przez zamkniętą krzywą, która zamyka się w sobie",
      "example": "El torus es una figura geométrica que se utiliza en física y matemáticas.",
      "example_translation": "Torus jest figurą geometryczną, która jest stosowana w fizyce i matematyce.",
      "imageLink": "https://www.ang.pl/img/slownik/torus.jpg",
      "audioLink": "https://www.ang.pl/sound/dict/torus.mp3"
    },
    {
      "section": "matematyka-terminy-matematyczne-po-angielsku",
      "language": "Spanish",
      "translationLanguage": "Polish",
      "word": "trapecio",
      "translation": "trapez",
      "definition": "Figura geométrica plana con cuatro lados, dos de los cuales son paralelos.",
      "definition_translation": "Plaska figura geometryczna z czterema bokami, dwoma z których są równoległe.",
      "example": "El trapecio es una figura común en la geometría.",
      "example_translation": "Trapez jest wspólną figurą w geometrii.",
      "imageLink": "https://www.ang.pl/img/slownik/trapezoid.jpg",
      "audioLink": "https://www.ang.pl/sound/dict/trapezoid.mp3"
    },
    {
      "section": "matematyka-terminy-matematyczne-po-angielsku",
      "language": "Spanish",
      "translationLanguage": "Polish",
      "word": "vector",
      "translation": "wektor",
      "definition": "Un vector es una magnitud con dirección y sentido.",
      "definition_translation": "Wektor jest wielkością z kierunkiem i sensownością.",
      "example": "El físico estudió el vector de la fuerza que actúa sobre el objeto.",
      "example_translation": "Fizyk studiował wektor siły, która działa na obiekt.",
      "imageLink": "https://www.ang.pl/img/slownik/vector.jpg",
      "audioLink": "https://www.ang.pl/sound/dict/vector.mp3"
    },
    {
      "section": "matematyka-terminy-matematyczne-po-angielsku",
      "language": "Spanish",
      "translationLanguage": "Polish",
      "word": "ángulo cero",
      "translation": "kąt zero",
      "definition": "Un ángulo cero es un ángulo que forma una línea recta.",
      "definition_translation": "Kąt zero to kąt, który tworzy prostą linię.",
      "example": "En geometría, el ángulo cero es importante para definir la posição de un objeto.",
      "example_translation": "W geometrii kąt zero jest ważny, aby zdefiniować położenie obiektu.",
      "imageLink": "https://www.ang.pl/img/slownik/zero-angle.jpg",
      "audioLink": "https://www.ang.pl/sound/dict/zero angle.mp3"
    }
  ]
}