{
  "data": [
    {
      "section": "znaki-zodiaku-po-French",
      "language": "French",
      "translationLanguage": "Polish",
      "word": "Aquarius",
      "translation": "Wodnik",
      "definition": "Le onzième signe du zodiaque, représenté par l'image d'un homme versant de l'eau.",
      "definition_translation": "Jedenasty znak zodiaku, reprezentowany przez obraz mężczyzny wylewającego wodę.",
      "example": "Le signe d'Aquarius correspond aux personnes nées entre le 20 janvier et le 18 février.",
      "example_translation": "Znak Wodnika odpowiada osobom urodzonym między 20 stycznia a 18 lutego.",
      "imageLink": "aquarius.jpg",
      "audioLink": "Aquarius.mp3"
    },
    {
      "section": "znaki-zodiaku-po-French",
      "language": "French",
      "translationLanguage": "Polish",
      "word": "Aries",
      "translation": "Baran",
      "definition": "Le signe du zodiaque correspondant au période du 21 mars au 19 avril.",
      "definition_translation": "Znaki zodiaku odpowiadający okresowi od 21 marca do 19 kwietnia.",
      "example": "Le symbole d'Aries est.",
      "example_translation": "Symbolem Barana jest.",
      "imageLink": "aries.jpg",
      "audioLink": "Aries.mp3"
    },
    {
      "section": "znaki-zodiaku-po-French",
      "language": "French",
      "translationLanguage": "Polish",
      "word": "Cancer",
      "translation": "Rak",
      "definition": "Maladie caractérisée par la prolifération anormale de cellules qui envahissent les tissus et les organes.",
      "definition_translation": "Choroba charakteryzująca się nieprawidłową proliferacją komórek, która zajmuje tkanki i narządy.",
      "example": "Le cancer est une maladie grave qui nécessite un traitement approprié.",
      "example_translation": "Rak jest poważną chorobą, która wymaga odpowiedniego leczenia.",
      "imageLink": "cancer.jpg",
      "audioLink": "Cancer.mp3"
    },
    {
      "section": "znaki-zodiaku-po-French",
      "language": "French",
      "translationLanguage": "Polish",
      "word": "Capricorn",
      "translation": "Koziorożec",
      "definition": "Dixième signe du zodiaque, correspondant au période du 22 décembre au 19 janvier.",
      "definition_translation": "Dziesiąty znak zodiaku, odpowiadający okresowi od 22 grudnia do 19 stycznia.",
      "example": "Le Capricorne est un signe de feu.",
      "example_translation": "Koziorożec jest znakiem ognia.",
      "imageLink": "capricorn.jpg",
      "audioLink": "Capricorn.mp3"
    },
    {
      "section": "znaki-zodiaku-po-French",
      "language": "French",
      "translationLanguage": "Polish",
      "word": "Gemini",
      "translation": "Bliźnięta",
      "definition": "Le sixième signe du zodiaque, représenté par les statues de deux frères.",
      "definition_translation": "Szósty znak zodiaku, reprezentowany przez posągi dwóch braci.",
      "example": "Le signe d'étoile de Gemini est un symbole de la dualité.",
      "example_translation": "Gwiazda znaku Bliźniąt jest symbolem dualności.",
      "imageLink": "gemini.jpg",
      "audioLink": "Gemini.mp3"
    },
    {
      "section": "znaki-zodiaku-po-French",
      "language": "French",
      "translationLanguage": "Polish",
      "word": "Léo",
      "translation": "Leo",
      "definition": "un prénom masculin qui signifie «lion» en latin",
      "definition_translation": "imię męskie, które oznacza «lew» po łacinie",
      "example": "Mon ami s'appelle Léo et il est très courageux.",
      "example_translation": "Mój przyjaciel nazywa się Leo i jest bardzo odważny.",
      "imageLink": "leo.jpg",
      "audioLink": "Leo.mp3"
    },
    {
      "section": "znaki-zodiaku-po-French",
      "language": "French",
      "translationLanguage": "Polish",
      "word": "Libra",
      "translation": "Waga",
      "definition": "Un signe du zodiaque ou une unité de masse.",
      "definition_translation": "Znaki zodiaku lub jednostka masy.",
      "example": "Le signe de la balance, ou Libra, correspond à la période du 23 septembre au 22 octobre.",
      "example_translation": "Znaki wag, lub Libra, odpowiada okresowi od 23 września do 22 października.",
      "imageLink": "libra.jpg",
      "audioLink": "Libra.mp3"
    },
    {
      "section": "znaki-zodiaku-po-French",
      "language": "French",
      "translationLanguage": "Polish",
      "word": "Poissons",
      "translation": "Ryby",
      "definition": "Les poissons sont des animaux aquatiques vertébrés",
      "definition_translation": "Ryby są wodnymi zwierzętami kręgowymi",
      "example": "Les poissons nagent dans l'eau.",
      "example_translation": "Ryby pływają w wodzie.",
      "imageLink": "pisces.jpg",
      "audioLink": "Pisces.mp3"
    },
    {
      "section": "znaki-zodiaku-po-French",
      "language": "French",
      "translationLanguage": "Polish",
      "word": "Sagittarius",
      "translation": "Strzelec",
      "definition": "Un signe du zodiaque entre Scorpius et Capricorne.",
      "definition_translation": "Znaki zodiaku między Skorpionem a Koziorożcem.",
      "example": "Le signe de mon frère est Sagittarius.",
      "example_translation": "Znakiem mojego brata jest Strzelec.",
      "imageLink": "sagittarius.jpg",
      "audioLink": "Sagittarius.mp3"
    },
    {
      "section": "znaki-zodiaku-po-French",
      "language": "French",
      "translationLanguage": "Polish",
      "word": "Scorpion",
      "translation": "Skorpion",
      "definition": "Zodiac sign, represented by a scorpion symbol",
      "definition_translation": "Znak zodiaku, reprezentowany przez symbol skorpiona",
      "example": "Je suis scorpio, donc je suis passionné.",
      "example_translation": "Jestem skorpionem, więc jestem pasjonatem.",
      "imageLink": "scorpio.jpg",
      "audioLink": "Scorpio.mp3"
    },
    {
      "section": "znaki-zodiaku-po-French",
      "language": "French",
      "translationLanguage": "Polish",
      "word": "Taurus",
      "translation": "Byk",
      "definition": "Un signe du zodiaque, représenté par un taureau.",
      "definition_translation": "Znaki zodiaku, przedstawiony przez byka.",
      "example": "Je suis né sous le signe du Taurus.",
      "example_translation": "Urodziłem się pod znakiem Byka.",
      "imageLink": "taurus.jpg",
      "audioLink": "Taurus.mp3"
    },
    {
      "section": "znaki-zodiaku-po-French",
      "language": "French",
      "translationLanguage": "Polish",
      "word": "Virgo",
      "translation": "Waga",
      "definition": "Le sixième signe du zodiaque, symbole de la jeune fille.",
      "definition_translation": "Szósty znak zodiaku, symbol dziewczyny.",
      "example": "Le signe de Virgo correspond à la période allant du 23 août au 22 septembre.",
      "example_translation": "Znak Wagi odpowiada okresowi od 23 sierpnia do 22 września.",
      "imageLink": "virgo.jpg",
      "audioLink": "Virgo.mp3"
    },
    {
      "section": "znaki-zodiaku-po-French",
      "language": "French",
      "translationLanguage": "Polish",
      "word": "signe du zodiaque",
      "translation": "znak zodiaku",
      "definition": "Chacun des douze secteurs dans lesquels le zodiaque est divisé.",
      "definition_translation": "Każdy z dwunastu sektorów, na które jest podzielony zodiak.",
      "example": "Le scrapy est mon signe du zodiaque.",
      "example_translation": "Skorpion jest moim znakiem zodiaku.",
      "imageLink": "zodiac-sign.jpg",
      "audioLink": "zodiac sign.mp3"
    }
  ]
}